MANIFEST.in
README.txt
setup.py
XStatic_JSON_js.egg-info/PKG-INFO
XStatic_JSON_js.egg-info/SOURCES.txt
XStatic_JSON_js.egg-info/dependency_links.txt
XStatic_JSON_js.egg-info/namespace_packages.txt
XStatic_JSON_js.egg-info/not-zip-safe
XStatic_JSON_js.egg-info/top_level.txt
xstatic/__init__.py
xstatic/pkg/__init__.py
xstatic/pkg/json_js/__init__.py
xstatic/pkg/json_js/data/README
xstatic/pkg/json_js/data/cycle.js
xstatic/pkg/json_js/data/json.js
xstatic/pkg/json_js/data/json2.js
xstatic/pkg/json_js/data/json_parse.js
xstatic/pkg/json_js/data/json_parse_state.js