Metadata-Version: 1.0
Name: XStatic-JSON-js
Version: 0.0.0.40f3377a63.1
Summary: JSON-js 40f3377a63 (XStatic packaging standard)
Home-page: https://github.com/douglascrockford/JSON-js
Author: Thomas Waldmann
Author-email: tw@waldmann-edv.de
License: (same as JSON-js)
Keywords: json_js xstatic
Platform: any
